README.md
setup.py
linux_tc/__init__.py
linux_tc/bandCalc.py
linux_tc/test_case.py
linux_tc/traffic_control.py
linux_tc.egg-info/PKG-INFO
linux_tc.egg-info/SOURCES.txt
linux_tc.egg-info/dependency_links.txt
linux_tc.egg-info/requires.txt
linux_tc.egg-info/top_level.txt