Metadata-Version: 2.1
Name: linux-tc
Version: 1.0.3
Summary: A toolchain for simulating weak network conditions
Home-page: UNKNOWN
Author:  MA JIANLI
Author-email: majianli@corp.netease.com
License: MIT
Platform: UNKNOWN
Classifier: Programming Language :: Python :: 3
Classifier: License :: OSI Approved :: MIT License
Classifier: Operating System :: OS Independent
Requires-Python: >=3.7
